python_tornet-2.2.0.dist-info/licenses/LICENSE
tornet/__init__.py
tornet/banner.py
tornet/test_sample.py
tornet/tornet.py
tornet/utils.py
python_tornet-2.2.0.dist-info/METADATA
python_tornet-2.2.0.dist-info/WHEEL
python_tornet-2.2.0.dist-info/entry_points.txt
python_tornet-2.2.0.dist-info/top_level.txt
python_tornet-2.2.0.dist-info/RECORD
