Metadata-Version: 2.4
Name: python-tornet
Version: 2.2.0
Summary: TorNet - Automate IP address changes using Tor
Home-page: https://github.com/ayadseghairi/tornet
Author: Ayad Seghiri
Author-email: seghiri.ayad@univ-khenchela.dz
Classifier: Programming Language :: Python :: 3
Classifier: License :: OSI Approved :: MIT License
Classifier: Operating System :: OS Independent
Requires-Python: >=3.6
License-File: LICENSE
Requires-Dist: requests
Requires-Dist: requests[socks]
Dynamic: author
Dynamic: author-email
Dynamic: classifier
Dynamic: description
Dynamic: description-content-type
Dynamic: home-page
Dynamic: license-file
Dynamic: requires-dist
Dynamic: requires-python
Dynamic: summary
